beakerx/__init__.py
beakerx/_version.py
beakerx/beakerx_autotranslation_server.py
beakerx/beakerx_server.py
beakerx/bkr2ipynb.py
beakerx/commands.py
beakerx/environment.py
beakerx/install.py
beakerx/jupyter_server_handlers.py
beakerx/kernel_spec.py
beakerx/runtime.py
beakerx/forms/__init__.py
beakerx/forms/easyforms.py
beakerx/forms/tests/__init__.py
beakerx/forms/tests/test_easyforms.py
beakerx/labextension/package.json
beakerx/labextension/static/089ab6d4a57e0e6c4dd3.ttf
beakerx/labextension/static/113.0c1bad23fdac0dc0d4f3.js
beakerx/labextension/static/302.e7a8b50cde94213c1464.js
beakerx/labextension/static/326.119199356a0706f5d877.js
beakerx/labextension/static/326.119199356a0706f5d877.js.LICENSE.txt
beakerx/labextension/static/346.2204310580567013ed67.js
beakerx/labextension/static/346.2204310580567013ed67.js.LICENSE.txt
beakerx/labextension/static/36.784caaec0c3258124dea.js
beakerx/labextension/static/406.a930e09da8d58b40d2e2.js
beakerx/labextension/static/42f3fd7ecbd1e18e5e9c.png
beakerx/labextension/static/445.b454418a8d039b523c90.js
beakerx/labextension/static/5b9025dda4d7688e3311.woff
beakerx/labextension/static/5eefdaf6178f3f466e74.woff
beakerx/labextension/static/61b1f210f3d2eb5c6bb3.woff
beakerx/labextension/static/659bd5ede5d3ef9c2373.woff
beakerx/labextension/static/69fdf4efd379a49f2d06.ttf
beakerx/labextension/static/6d81fc3fac3b17a25f4e.png
beakerx/labextension/static/6efc1db612130b63222e.png
beakerx/labextension/static/700.94726ea8d37c2b61ac41.js
beakerx/labextension/static/755.3f8daad4c763c77a4ee1.js
beakerx/labextension/static/755.3f8daad4c763c77a4ee1.js.LICENSE.txt
beakerx/labextension/static/794.96c35caa97202c5357d8.js
beakerx/labextension/static/798.fb209caf2c2a89e52480.js
beakerx/labextension/static/842.970fccdbb4303aad19bd.js
beakerx/labextension/static/86bfafd51a8ef528d257.ttf
beakerx/labextension/static/91e1ea5f253e72e2e940.png
beakerx/labextension/static/943d9bc18134619d3740.png
beakerx/labextension/static/9dab1725ee38e87989a4.png
beakerx-2.4.3.dist-info/LICENSE
beakerx-2.4.3.dist-info/METADATA
beakerx-2.4.3.dist-info/WHEEL
beakerx-2.4.3.dist-info/entry_points.txt
beakerx-2.4.3.dist-info/top_level.txt
beakerx-2.4.3.dist-info/RECORD
